tbl/__init__.py
tbl/cli.py
tbl/main.py
clitbl-0.0.1.dist-info/LICENSE
clitbl-0.0.1.dist-info/METADATA
clitbl-0.0.1.dist-info/WHEEL
clitbl-0.0.1.dist-info/entry_points.txt
clitbl-0.0.1.dist-info/top_level.txt
clitbl-0.0.1.dist-info/RECORD
