Metadata-Version: 2.1
Name: clitbl
Version: 0.0.1
Summary: csv files printer
Home-page: https://github.com/ronserruya/tbl
Author: Ron Serruya
Author-email: ron.serruya@gmail.com
License: UNKNOWN
Platform: UNKNOWN
Classifier: Programming Language :: Python :: 3
Classifier: License :: OSI Approved :: MIT License
Classifier: Operating System :: OS Independent
Requires-Python: >=3.4
Requires-Dist: rapidtables (==0.1.7)
Requires-Dist: click (==7)
